cyyrus/__init__.py
cyyrus/__version__.py
cyyrus/cli/__init__.py
cyyrus/cli/main.py
cyyrus/cli/utils.py
cyyrus/cli/visualizer.py
cyyrus/composer/__init__.py
cyyrus/composer/core.py
cyyrus/composer/dataframe.py
cyyrus/composer/dataset.py
cyyrus/composer/markdown.py
cyyrus/composer/progress.py
cyyrus/composer/utils.py
cyyrus/constants/__init__.py
cyyrus/constants/messages.py
cyyrus/models/__init__.py
cyyrus/models/column.py
cyyrus/models/dataset.py
cyyrus/models/options.py
cyyrus/models/spec.py
cyyrus/models/task.py
cyyrus/models/task_type.py
cyyrus/models/types.py
cyyrus/tasks/__init__.py
cyyrus/tasks/base.py
cyyrus/tasks/default.py
cyyrus/tasks/generation.py
cyyrus/tasks/parsing.py
cyyrus/tasks/utils.py
cyyrus/utils/__init__.py
cyyrus/utils/errors.py
cyyrus/utils/logging.py
cyyrus/utils/mermaid.py
extras/__init__.py
extras/pre_install.py
cyyrus-0.20.0.dist-info/LICENSE
cyyrus-0.20.0.dist-info/METADATA
cyyrus-0.20.0.dist-info/WHEEL
cyyrus-0.20.0.dist-info/entry_points.txt
cyyrus-0.20.0.dist-info/top_level.txt
cyyrus-0.20.0.dist-info/RECORD
