Metadata-Version: 2.1
Name: cyyrus
Version: 0.20.0
Summary: Transform Unstructured Data into Usable Datasets
Home-page: https://github.com/wizenheimer/cyyrus
Author: wizenheimer
Author-email: cyyruslabs@gmail.com
License-File: LICENSE
Requires-Dist: click ==8.1.7
Requires-Dist: pydantic ==2.8.2
Requires-Dist: datasets ==2.21.0
Requires-Dist: python-dotenv ==1.0.1
Requires-Dist: pillow ==10.4.0
Requires-Dist: pydub ==0.25.1
Requires-Dist: pdf2image ==1.17.0
Requires-Dist: openai ==1.42.0
Requires-Dist: colorlog ==6.8.2
Requires-Dist: python-json-logger ==2.0.7
Requires-Dist: tqdm ==4.66.5
Requires-Dist: huggingface-hub ==0.24.6
Requires-Dist: rich ==13.8.0
